lib/__init__.py
lib/crypno.py
crypno-1.0.0.dist-info/LICENSE
crypno-1.0.0.dist-info/METADATA
crypno-1.0.0.dist-info/WHEEL
crypno-1.0.0.dist-info/top_level.txt
crypno-1.0.0.dist-info/RECORD
